vidcontrol/__init__.py
vidcontrol/video_manager.py
vidcontrol/video_platform.py
vidcontrol/video_source.py
vidcontrol/platforms/__init__.py
vidcontrol/platforms/base.py
vidcontrol/platforms/linux.py
vidcontrol/platforms/mac.py
vidcontrol/platforms/win.py
vidcontrol/util/__init__.py
vidcontrol/util/subprocess.py
vidcontrol-0.1.2.dist-info/LICENSE.md
vidcontrol-0.1.2.dist-info/METADATA
vidcontrol-0.1.2.dist-info/WHEEL
vidcontrol-0.1.2.dist-info/top_level.txt
vidcontrol-0.1.2.dist-info/RECORD
