Metadata-Version: 2.1
Name: vidcontrol
Version: 0.1.2
Summary: Cross platform multi-webcam video capture utility.
Home-page: https://github.com/inmotion-health/vidcontrol
Author: Fabian S. Klinke
Author-email: fabian.s.klinke@inmotion.health
License: MIT
Project-URL: Bug Tracker, https://github.com/inmotion-health/vidcontrol/issues
Project-URL: Source Code, https://github.com/inmotion-health/vidcontrol
Classifier: Programming Language :: Python :: 3.8
Classifier: License :: OSI Approved :: MIT License
Classifier: Operating System :: OS Independent
Requires-Python: >=3.8
License-File: LICENSE.md
Requires-Dist: numpy
Requires-Dist: imageio
Requires-Dist: opencv-python
Requires-Dist: imageio-ffmpeg
Requires-Dist: pygrabber
